{
	"code": "winged-tiara",
	"class": "ItemWearable",
	"shape": {
		"base": "game:entity/humanoid/seraph/clothing/head/silver-diadem"
	},
	"textures": {
		"*": { "base": "game:block/metal/ingot/silver" }
	},
	"storageFlags": 128,
	"attributes": {
		"wearableAttachment": true,
		"clothingType": "head",
		"warmth": 0
	},
	"creativeinventory": {
		"general": [ "*" ],
		"items": [ "*" ],
		"clothing": [ "*" ]
	},
	"guiTransform": {
		"rotation": {
			"x": -22.5,
			"y": -40,
			"z": 0
		},
		"origin": {
			"x": 0.5,
			"y": 0.1,
			"z": 0.5
		},
		"scale": 3.1
	},
	"fpHandTransform": {
		"translation": {
			"x": 0,
			"y": 0,
			"z": 0
		},
		"rotation": {
			"x": 15,
			"y": 15,
			"z": -15
		},
		"scale": 2.5
	},
	"tpHandTransform": {
		"translation": {
			"x": -0.85,
			"y": -0.4,
			"z": -0.45
		},
		"rotation": {
			"x": -68,
			"y": 27,
			"z": -101
		},
		"scale": 0.65
	},
	"groundTransform": {
		"rotation": {
			"x": 0,
			"y": 0,
			"z": 0
		},
		"origin": {
			"x": 0.5,
			"y": 0.15,
			"z": 0.5
		},
		"scale": 3.5
	}
}