[
	{
		"file": "game:itemtypes/resource/metalbit.json",
		"op": "add",
		"path": "/combustiblePropsByType/*-manasteel",
		"value": {
			"meltingPoint": 1084,
			"meltingDuration": 30,
			"smeltedRatio": 20,
			"smeltedStack": {
				"type": "item",
				"code": "game:ingot-manasteel"
			}
		}
	},
	{
		"file": "game:itemtypes/resource/metalbit.json",
		"op": "add",
		"path": "/combustiblePropsByType/*-terrasteel",
		"value": {
			"meltingPoint": 1502,
			"meltingDuration": 30,
			"smeltedRatio": 20,
			"smeltedStack": {
				"type": "item",
				"code": "game:ingot-terrasteel"
			}
		}
	},
	{
		"file": "game:itemtypes/resource/metalbit.json",
		"op": "add",
		"path": "/combustiblePropsByType/*-elementium",
		"value": {
			"meltingPoint": 1482,
			"meltingDuration": 30,
			"smeltedRatio": 20,
			"smeltedStack": {
				"type": "item",
				"code": "game:ingot-elementium"
			}
		}
	},
	{
		"file": "game:itemtypes/resource/metalbit.json",
		"op": "add",
		"path": "/creativeinventory/botaniastory",
		"value": [ "*-manasteel", "*-terrasteel", "*-elementium" ]
	}
]