[
    {
        "ingredientPattern": "IRS",
        "ingredients": {
            "I": {
                "type": "item",
                "code": "game:ingot-manasteel"
            },
            "R": {
                "type": "item",
                "code": "botaniastory:rune-water"
            },
            "S": {
                "type": "item",
                "code": "game:stick"
            }
        },
        "width": 3,
        "height": 1,
        "output": {
            "type": "item",
            "code": "botaniastory:sparkaugment-dispersive",
            "quantity": 1
        }
    },
    {
        "ingredientPattern": "IRS",
        "ingredients": {
            "I": {
                "type": "item",
                "code": "game:ingot-manasteel"
            },
            "R": {
                "type": "item",
                "code": "botaniastory:rune-fire"
            },
            "S": {
                "type": "item",
                "code": "game:stick"
            }
        },
        "width": 3,
        "height": 1,
        "output": {
            "type": "item",
            "code": "botaniastory:sparkaugment-dominant",
            "quantity": 1
        }
    },
    {
        "ingredientPattern": "IRS",
        "ingredients": {
            "I": {
                "type": "item",
                "code": "game:ingot-manasteel"
            },
            "R": {
                "type": "item",
                "code": "botaniastory:rune-air"
            },
            "S": {
                "type": "item",
                "code": "game:stick"
            }
        },
        "width": 3,
        "height": 1,
        "output": {
            "type": "item",
            "code": "botaniastory:sparkaugment-isolated",
            "quantity": 1
        }
    },
    {
        "ingredientPattern": "IRS",
        "ingredients": {
            "I": {
                "type": "item",
                "code": "game:ingot-manasteel"
            },
            "R": {
                "type": "item",
                "code": "botaniastory:rune-earth"
            },
            "S": {
                "type": "item",
                "code": "game:stick"
            }
        },
        "width": 3,
        "height": 1,
        "output": {
            "type": "item",
            "code": "botaniastory:sparkaugment-recessive",
            "quantity": 1
        }
    }
]